podcastparser.py
podcastparser-0.6.11.dist-info/licenses/AUTHORS
podcastparser-0.6.11.dist-info/licenses/LICENSE
podcastparser-0.6.11.dist-info/METADATA
podcastparser-0.6.11.dist-info/WHEEL
podcastparser-0.6.11.dist-info/top_level.txt
podcastparser-0.6.11.dist-info/RECORD
