Metadata-Version: 2.4
Name: podcastparser
Version: 0.6.11
Summary:  Simplified, fast RSS parser 
Home-page: http://gpodder.org/podcastparser/
Author: Thomas Perl
Author-email: m@thp.io
License: ISC License
License-File: LICENSE
License-File: AUTHORS
Dynamic: author
Dynamic: author-email
Dynamic: description
Dynamic: description-content-type
Dynamic: home-page
Dynamic: license
Dynamic: license-file
Dynamic: summary
